[
    {
        "id": 3861,
        "date": "2024-03-08",
        "name": "patient_1",
        "age": "35",
        "gender": "female",
        "fmnameHead": "W/o",
        "fmname": "Name_1",
        "street": "example street",
        "village": "village name",
        "phone": "0000000000"
    },
    {
        "id": 3871,
        "date": "2024-01-15",
        "name": "patient_2",
        "age": "28",
        "gender": "male",
        "fmnameHead": "S/o",
        "fmname": "Name_2",
        "street": "sample street",
        "village": "town name",
        "phone": "1111111111"
    },
    {
        "id": 3881,
        "date": "2024-06-02",
        "name": "patient_3",
        "age": "42",
        "gender": "female",
        "fmnameHead": "W/o",
        "fmname": "Name_3",
        "street": "another street",
        "village": "another village",
        "phone": "2222222222"
    },
    {
        "id": 3891,
        "date": "2024-04-18",
        "name": "patient_4",
        "age": "31",
        "gender": "male",
        "fmnameHead": "S/o",
        "fmname": "Name_4",
        "street": "some street",
        "village": "some village",
        "phone": "3333333333"
    },
    {
        "id": 3901,
        "date": "2024-08-10",
        "name": "patient_5",
        "age": "55",
        "gender": "female",
        "fmnameHead": "W/o",
        "fmname": "Name_5",
        "street": "example street",
        "village": "village name",
        "phone": "4444444444"
    },
    {
        "id": 3911,
        "date": "2024-02-29",
        "name": "patient_6",
        "age": "40",
        "gender": "male",
        "fmnameHead": "S/o",
        "fmname": "Name_6",
        "street": "sample street",
        "village": "town name",
        "phone": "5555555555"
    },
    {
        "id": 3921,
        "date": "2024-07-17",
        "name": "patient_7",
        "age": "48",
        "gender": "female",
        "fmnameHead": "W/o",
        "fmname": "Name_7",
        "street": "another street",
        "village": "another village",
        "phone": "6666666666"
    },
    {
        "id": 3931,
        "date": "2024-05-05",
        "name": "patient_8",
        "age": "25",
        "gender": "male",
        "fmnameHead": "S/o",
        "fmname": "Name_8",
        "street": "some street",
        "village": "some village",
        "phone": "7777777777"
    },
    {
        "id": 3941,
        "date": "2024-09-22",
        "name": "patient_9",
        "age": "37",
        "gender": "female",
        "fmnameHead": "W/o",
        "fmname": "Name_9",
        "street": "example street",
        "village": "village name",
        "phone": "8888888888"
    },
    {
        "id": 3951,
        "date": "2024-03-14",
        "name": "patient_10",
        "age": "32",
        "gender": "male",
        "fmnameHead": "S/o",
        "fmname": "Name_10",
        "street": "sample street",
        "village": "town name",
        "phone": "9999999999"
    },
    {
        "id": 3961,
        "date": "2024-10-05",
        "name": "patient_11",
        "age": "50",
        "gender": "female",
        "fmnameHead": "W/o",
        "fmname": "Name_11",
        "street": "another street",
        "village": "another village",
        "phone": "1010101010"
    },
    {
        "id": 3971,
        "date": "2024-12-01",
        "name": "patient_12",
        "age": "29",
        "gender": "male",
        "fmnameHead": "S/o",
        "fmname": "Name_12",
        "street": "some street",
        "village": "some village",
        "phone": "1111222233"
    },
    {
        "id": 3981,
        "date": "2024-11-11",
        "name": "patient_13",
        "age": "45",
        "gender": "female",
        "fmnameHead": "W/o",
        "fmname": "Name_13",
        "street": "example street",
        "village": "village name",
        "phone": "1212121212"
    },
    {
        "id": 3991,
        "date": "2024-08-25",
        "name": "patient_14",
        "age": "36",
        "gender": "male",
        "fmnameHead": "S/o",
        "fmname": "Name_14",
        "street": "sample street",
        "village": "town name",
        "phone": "1313131313"
    },
    {
        "id": 4001,
        "date": "2024-04-03",
        "name": "patient_15",
        "age": "47",
        "gender": "female",
        "fmnameHead": "W/o",
        "fmname": "Name_15",
        "street": "another street",
        "village": "another village",
        "phone": "1414141414"
    },
    {
        "id": 4011,
        "date": "2024-09-18",
        "name": "patient_16",
        "age": "30",
        "gender": "male",
        "fmnameHead": "S/o",
        "fmname": "Name_16",
        "street": "some street",
        "village": "some village",
        "phone": "1515151515"
    },
    {
        "id": 4021,
        "date": "2024-07-09",
        "name": "patient_17",
        "age": "41",
        "gender": "female",
        "fmnameHead": "W/o",
        "fmname": "Name_17",
        "street": "example street",
        "village": "village name",
        "phone": "1616161616"
    },
    {
        "id": 4031,
        "date": "2024-02-22",
        "name": "patient_18",
        "age": "34",
        "gender": "male",
        "fmnameHead": "S/o",
        "fmname": "Name_18",
        "street": "sample street",
        "village": "town name",
        "phone": "1717171717"
    },
    {
        "id": 4041,
        "date": "2024-10-18",
        "name": "patient_19",
        "age": "49",
        "gender": "female",
        "fmnameHead": "W/o",
        "fmname": "Name_19",
        "street": "another street",
        "village": "another village",
        "phone": "1818181818"
    },
    {
        "id": 4051,
        "date": "2024-05-12",
        "name": "patient_20",
        "age": "33",
        "gender": "male",
        "fmnameHead": "H/o",
        "fmname": "Name_20",
        "street": "some street",
        "village": "some village",
        "phone": "1919191919"
    }
]
